{
    "status_code": 10,
    "lang": "typescript",
    "run_success": true,
    "status_runtime": "60 ms",
    "memory": 50612000,
    "question_id": "2955",
    "elapsed_time": 78,
    "compare_result": "11111111111111111111111111111111111111111111111111111111111111111111111111111111111111111111111111111",
    "code_output": "",
    "std_output": "",
    "last_testcase": "",
    "expected_output": "",
    "task_finish_time": 1706035940154,
    "task_name": "judger.judgetask.Judge",
    "finished": true,
    "total_correct": 101,
    "total_testcases": 101,
    "runtime_percentile": 55.172299999999986,
    "status_memory": "50.6 MB",
    "memory_percentile": 6.89639999999998,
    "pretty_lang": "TypeScript",
    "submission_id": "1154888023",
    "status_msg": "Accepted",
    "state": "SUCCESS",
    "code": "function accountBalanceAfterPurchase(purchaseAmount: number): number {\n    let initialBalance = 100;\n    let roundedAmount: number;\n\n    // Determine the nearest multiple of 10, rounding up if the remainder is 5 or more\n    if (purchaseAmount % 10 >= 5) {\n        roundedAmount = purchaseAmount + (10 - purchaseAmount % 10);\n    } else {\n        roundedAmount = purchaseAmount - (purchaseAmount % 10);\n    }\n\n    return initialBalance - roundedAmount;\n};"
}