{
    "status_code": 20,
    "lang": "java",
    "run_success": false,
    "compile_error": "Line 16: error: int cannot be dereferenced",
    "full_compile_error": "Line 16: error: int cannot be dereferenced\n                if (Math.abs(evenCount - oddCount) > tempNum.toString().length()) {\n                                                            ^",
    "status_runtime": "N/A",
    "memory": 0,
    "question_id": "3017",
    "task_finish_time": 1708932717457,
    "task_name": "judger.judgetask.Judge",
    "finished": true,
    "total_correct": null,
    "total_testcases": null,
    "runtime_percentile": null,
    "status_memory": "N/A",
    "memory_percentile": null,
    "pretty_lang": "Java",
    "submission_id": "1186505948",
    "status_msg": "Compile Error",
    "state": "SUCCESS",
    "code": "class Solution {\n    public int numberOfBeautifulIntegers(int low, int high, int k) {\n        int count = 0;\n        for (int num = low; num <= high; num++) {\n            if (num % k != 0) continue; // Skip numbers not divisible by k\n            \n            int evenCount = 0, oddCount = 0, tempNum = num;\n            boolean isBeautiful = true;\n            \n            while (tempNum > 0) {\n                int digit = tempNum % 10;\n                if (digit % 2 == 0) evenCount++;\n                else oddCount++;\n                \n                tempNum /= 10;\n                if (Math.abs(evenCount - oddCount) > tempNum.toString().length()) {\n                    isBeautiful = false;\n                    break;\n                }\n            }\n            \n            if (evenCount == oddCount && isBeautiful) count++;\n        }\n        return count;\n    }\n}"
}